COPYING
MANIFEST.in
README
README.rst
setup.cfg
setup.py
static.py
static3_jl.egg-info/PKG-INFO
static3_jl.egg-info/SOURCES.txt
static3_jl.egg-info/dependency_links.txt
static3_jl.egg-info/entry_points.txt
static3_jl.egg-info/requires.txt
static3_jl.egg-info/top_level.txt
testdata/priv/foo.txt
testdata/pub/encoding.html.genshi
testdata/pub/favicon.ico
testdata/pub/index.html
testdata/pub/kid.html.kid
testdata/pub/sub.html.stp
testdata/pub/test.html.genshi
testdata/pub/test.xml
testdata/pub/unicode.html